pyphenotyper/__init__.py
pyphenotyper/assets/seeding_template.tif
pyphenotyper/data/__init__.py
pyphenotyper/data/data_processing.py
pyphenotyper/data/logger_config.py
pyphenotyper/features/__init__.py
pyphenotyper/features/features.py
pyphenotyper/features/graph.py
pyphenotyper/features/logger_config.py
pyphenotyper/features/primary_root.ipynb
pyphenotyper/features/roots_segmentation.py
pyphenotyper/features/rsml.py
pyphenotyper/logger_config.py
pyphenotyper/main.ipynb
pyphenotyper/model_refrence/__init__.py
pyphenotyper/model_refrence/occlusion_rs_1_256.h5
pyphenotyper/model_refrence/root_4_ss.h5
pyphenotyper/model_refrence/shoot_exp_1.h5
pyphenotyper/pipelines/__init__.py
pyphenotyper/pipelines/data_generators.py
pyphenotyper/pipelines/data_prep_pipeline.py
pyphenotyper/pipelines/evaluation_pipeline.py
pyphenotyper/pipelines/model.py
pyphenotyper/pipelines/plotting.py
pyphenotyper/pipelines/train_model.py
pyphenotyper/pipelines/training_pipeline.py
pyphenotyper/utils/__init__.py
pyphenotyper/utils/helpers.py
pyphenotyper/utils/logger_config.py
pyphenotyper/utils/metrics.py
pyphenotyper-0.1.2.dist-info/METADATA
pyphenotyper-0.1.2.dist-info/WHEEL
pyphenotyper-0.1.2.dist-info/RECORD
