Metadata-Version: 2.1
Name: pyphenotyper
Version: 0.1.2
Summary: NPEC pipeline
Author: Borislav Nachev
Author-email: 220472@buas.nl
Requires-Python: >=3.10.0,<=3.10.14
Classifier: Programming Language :: Python :: 3
Classifier: Programming Language :: Python :: 3.10
Requires-Dist: matplotlib (>=3.8.4,<4.0.0)
Requires-Dist: nbformat (>=5.10.4,<6.0.0)
Requires-Dist: networkx (>=3.3,<4.0)
Requires-Dist: numpy (==1.23.5)
Requires-Dist: opencv-python (>=4.9.0.80,<5.0.0.0)
Requires-Dist: pandas (>=2.2.2,<3.0.0)
Requires-Dist: patchify (>=0.2.3,<0.3.0)
Requires-Dist: plotly (>=5.22.0,<6.0.0)
Requires-Dist: rich (==13.7.0)
Requires-Dist: scikit-image (>=0.23.2,<0.24.0)
Requires-Dist: scipy (>=1.13.1,<2.0.0)
Requires-Dist: skan (>=0.11.1,<0.12.0)
Requires-Dist: tensorflow (==2.10.0) ; sys_platform == "linux" or sys_platform == "win32"
Requires-Dist: tensorflow-intel (==2.10.0) ; sys_platform == "win32"
Requires-Dist: tensorflow-io-gcs-filesystem (==0.30.0) ; sys_platform == "linux" or sys_platform == "win32"
Requires-Dist: tensorflow-macos (==2.10.0) ; sys_platform == "darwin"
Requires-Dist: typer (>=0.9.0,<0.10.0)
